gistcafe/__init__.py
gistcafe/inspect.py
tests/__init__.py
tests/test_api.py
gistcafe-0.0.3.dist-info/LICENSE
gistcafe-0.0.3.dist-info/METADATA
gistcafe-0.0.3.dist-info/WHEEL
gistcafe-0.0.3.dist-info/top_level.txt
gistcafe-0.0.3.dist-info/RECORD
