Metadata-Version: 2.1
Name: gistcafe
Version: 0.0.3
Summary: gist.cafe utils for Python
Home-page: https://github.com/ServiceStack/gistcafe-python
Author: ServiceStack, Inc.
Author-email: team@servicestack.net
License: BSD-3-Clause
Keywords: gistcafe,dump,prettyprint
Platform: UNKNOWN
Classifier: Intended Audience :: Developers
Classifier: License :: OSI Approved :: BSD License
Classifier: Natural Language :: English
Classifier: Operating System :: OS Independent
Classifier: Programming Language :: Python :: 3.5
Classifier: Programming Language :: Python :: 3.6
Classifier: Programming Language :: Python :: 3.7
Classifier: Programming Language :: Python :: 3.8
Classifier: Topic :: Software Development :: Libraries :: Python Modules
Requires-Python: >=3.5
Requires-Dist: dataclasses-json (>=0.5.2)
Requires-Dist: tabulate (>=0.8.7)
